distributed_discovery/__init__.py
distributed_discovery/discover.py
distributed_discovery/view.py
distributed_discovery/conversion/__init__.py
distributed_discovery/conversion/bpmn.py
distributed_discovery/conversion/petri_net.py
distributed_discovery/discovery/__init__.py
distributed_discovery/discovery/dfg.py
distributed_discovery/discovery/im.py
distributed_discovery/discovery/message_flow.py
distributed_discovery/export/__init__.py
distributed_discovery/export/bpmn.py
distributed_discovery/export/layout.py
distributed_discovery/objects/__init__.py
distributed_discovery/objects/dfg.py
distributed_discovery/objects/log.py
distributed_discovery/objects/message_activity.py
distributed_discovery/objects/message_flow.py
distributed_discovery/objects/process_tree.py
distributed_discovery/objects/process_tree_operator.py
distributed_discovery/util/__init__.py
distributed_discovery/util/bpmn.py
distributed_discovery/util/constants.py
distributed_discovery/util/filter.py
distributed_discovery/util/process_tree.py
distributed_discovery/util/read.py
distributed_discovery/visualization/__init__.py
distributed_discovery/visualization/bpmn.py
distributed_discovery/visualization/dfg.py
distributed_discovery/visualization/petri_net.py
distributed_discovery/visualization/process_tree.py
distributed_discovery/visualization/assets/__init__.py
distributed_discovery/visualization/assets/envelope.svg
distributed_discovery/visualization/assets/envelope_full.svg
tests/__init__.py
tests/test_bpmn.py
tests/test_bpmn_export.py
tests/test_bpmn_visualization.py
tests/test_dfg.py
tests/test_dfg_visualization.py
tests/test_distributed_event_log.py
tests/test_distributed_traces.py
tests/test_import.py
tests/test_petri_net_visualization.py
tests/test_process_tree.py
tests/test_process_tree_visualization.py
distributed_discovery-0.0.1.dist-info/LICENSE
distributed_discovery-0.0.1.dist-info/METADATA
distributed_discovery-0.0.1.dist-info/WHEEL
distributed_discovery-0.0.1.dist-info/top_level.txt
distributed_discovery-0.0.1.dist-info/RECORD
